cedarscript_editor/__init__.py
cedarscript_editor/case_filter.py
cedarscript_editor/cedarscript_editor.py
cedarscript_editor/ed_script_filter.py
cedarscript_editor/tree_sitter_identifier_finder.py
cedarscript_editor/tree_sitter_identifier_queries.py
text_manipulation/__init__.py
text_manipulation/cst_kit.py
text_manipulation/indentation_kit.py
text_manipulation/line_kit.py
text_manipulation/range_spec.py
text_manipulation/text_editor_kit.py
version/__init__.py
version/_version.py
cedarscript_editor-1.3.5.dist-info/LICENSE
cedarscript_editor-1.3.5.dist-info/METADATA
cedarscript_editor-1.3.5.dist-info/WHEEL
cedarscript_editor-1.3.5.dist-info/top_level.txt
cedarscript_editor-1.3.5.dist-info/RECORD
