Metadata-Version: 2.1
Name: cedarscript-editor
Version: 1.3.5
Summary: A library for executing CEDARScript, a SQL-like language for code analysis and transformations
Author-email: Elifarley <cedarscript@orgecc.com>
License: Apache-2.0
Project-URL: Homepage, https://github.com/CEDARScript/cedarscript-editor-python
Project-URL: Documentation, https://github.com/CEDARScript/cedarscript-editor-python#readme
Project-URL: Repository, https://github.com/CEDARScript/cedarscript-editor-python.git
Project-URL: Bug Tracker, https://github.com/CEDARScript/cedarscript-editor-python/issues
Keywords: cedarscript,code-editing,refactoring,code-analysis,sql-like,ai-assisted-development
Classifier: Programming Language :: Python :: 3
Classifier: Programming Language :: Python :: 3.12
Classifier: License :: OSI Approved :: Apache Software License
Classifier: Operating System :: OS Independent
Classifier: Intended Audience :: Developers
Classifier: Topic :: Software Development :: Libraries :: Python Modules
Classifier: Topic :: Text Processing :: Linguistic
Classifier: Topic :: Software Development :: Code Generators
Classifier: Topic :: Software Development :: Compilers
Requires-Python: >=3.11
License-File: LICENSE
Requires-Dist: orgecc-pylib>=0.1.3
Requires-Dist: cedarscript-ast-parser>=0.7.0
Requires-Dist: grep-ast==0.4.1
Requires-Dist: tree-sitter==0.21.3
Requires-Dist: tree-sitter-languages==1.10.2
Provides-Extra: dev
Requires-Dist: pytest>=7.0; extra == "dev"
Requires-Dist: pytest-cov>=6.0.0; extra == "dev"
Requires-Dist: black>=22.0; extra == "dev"
Requires-Dist: isort>=5.0; extra == "dev"
Requires-Dist: flake8>=4.0; extra == "dev"
Requires-Dist: mypy>=0.900; extra == "dev"
Requires-Dist: coverage>=6.0; extra == "dev"
Requires-Dist: tox>=3.24; extra == "dev"
